{
  "format_version": "1.12.0",
  "minecraft:geometry": [
    {
      "description": {
        "identifier": "geometry.zcbutton",
        "texture_width": 16,
        "texture_height": 16,
        "visible_bounds_width": 2,
        "visible_bounds_height": 3.5,
        "visible_bounds_offset": [
          0,
          1.25,
          0
        ]
      },
      "bones": [
        {
          "name": "floor_off",
          "pivot": [
            2,
            0,
            1
          ],
          "cubes": [
            {
              "origin": [
                -3,
                0,
                -2
              ],
              "size": [
                6,
                2,
                4
              ],
              "uv": {
                "north": {
                  "uv": [
                    4,
                    7
                  ],
                  "uv_size": [
                    6,
                    2
                  ]
                },
                "east": {
                  "uv": [
                    0,
                    7
                  ],
                  "uv_size": [
                    4,
                    2
                  ]
                },
                "south": {
                  "uv": [
                    10,
                    9
                  ],
                  "uv_size": [
                    6,
                    2
                  ]
                },
                "west": {
                  "uv": [
                    10,
                    7
                  ],
                  "uv_size": [
                    4,
                    2
                  ]
                },
                "up": {
                  "uv": [
                    8,
                    6
                  ],
                  "uv_size": [
                    6,
                    4
                  ]
                },
                "down": {
                  "uv": [
                    10,
                    7
                  ],
                  "uv_size": [
                    6,
                    -4
                  ]
                }
              }
            }
          ]
        },
        {
          "name": "floor_on",
          "pivot": [
            2,
            0,
            1
          ],
          "cubes": [
            {
              "origin": [
                -3,
                0,
                -2
              ],
              "size": [
                6,
                1,
                4
              ],
              "uv": {
                "north": {
                  "uv": [
                    4,
                    8
                  ],
                  "uv_size": [
                    6,
                    1
                  ]
                },
                "east": {
                  "uv": [
                    0,
                    8
                  ],
                  "uv_size": [
                    4,
                    1
                  ]
                },
                "south": {
                  "uv": [
                    10,
                    10
                  ],
                  "uv_size": [
                    6,
                    1
                  ]
                },
                "west": {
                  "uv": [
                    10,
                    8
                  ],
                  "uv_size": [
                    4,
                    1
                  ]
                },
                "up": {
                  "uv": [
                    8,
                    6
                  ],
                  "uv_size": [
                    6,
                    4
                  ]
                },
                "down": {
                  "uv": [
                    10,
                    7
                  ],
                  "uv_size": [
                    6,
                    -4
                  ]
                }
              }
            }
          ]
        },
        {
          "name": "wall_off",
          "pivot": [
            2,
            9,
            8
          ],
          "rotation": [
            90,
            0,
            0
          ],
          "cubes": [
            {
              "origin": [
                -3,
                9,
                5
              ],
              "size": [
                6,
                2,
                4
              ],
              "uv": {
                "north": {
                  "uv": [
                    4,
                    7
                  ],
                  "uv_size": [
                    6,
                    2
                  ]
                },
                "east": {
                  "uv": [
                    0,
                    7
                  ],
                  "uv_size": [
                    4,
                    2
                  ]
                },
                "south": {
                  "uv": [
                    10,
                    9
                  ],
                  "uv_size": [
                    6,
                    2
                  ]
                },
                "west": {
                  "uv": [
                    10,
                    7
                  ],
                  "uv_size": [
                    4,
                    2
                  ]
                },
                "up": {
                  "uv": [
                    8,
                    6
                  ],
                  "uv_size": [
                    6,
                    4
                  ]
                },
                "down": {
                  "uv": [
                    10,
                    7
                  ],
                  "uv_size": [
                    6,
                    -4
                  ]
                }
              }
            }
          ]
        },
        {
          "name": "wall_on",
          "pivot": [
            2,
            9,
            8
          ],
          "rotation": [
            90,
            0,
            0
          ],
          "cubes": [
            {
              "origin": [
                -3,
                9,
                5
              ],
              "size": [
                6,
                1,
                4
              ],
              "uv": {
                "north": {
                  "uv": [
                    4,
                    8
                  ],
                  "uv_size": [
                    6,
                    1
                  ]
                },
                "east": {
                  "uv": [
                    0,
                    8
                  ],
                  "uv_size": [
                    4,
                    1
                  ]
                },
                "south": {
                  "uv": [
                    10,
                    10
                  ],
                  "uv_size": [
                    6,
                    1
                  ]
                },
                "west": {
                  "uv": [
                    10,
                    8
                  ],
                  "uv_size": [
                    4,
                    1
                  ]
                },
                "up": {
                  "uv": [
                    8,
                    6
                  ],
                  "uv_size": [
                    6,
                    4
                  ]
                },
                "down": {
                  "uv": [
                    10,
                    7
                  ],
                  "uv_size": [
                    6,
                    -4
                  ]
                }
              }
            }
          ]
        },
        {
          "name": "roof_off",
          "pivot": [
            0,
            15,
            0
          ],
          "rotation": [
            180,
            0,
            0
          ],
          "cubes": [
            {
              "origin": [
                -3,
                14,
                -2
              ],
              "size": [
                6,
                2,
                4
              ],
              "uv": {
                "north": {
                  "uv": [
                    4,
                    8
                  ],
                  "uv_size": [
                    6,
                    1
                  ]
                },
                "east": {
                  "uv": [
                    0,
                    8
                  ],
                  "uv_size": [
                    4,
                    1
                  ]
                },
                "south": {
                  "uv": [
                    10,
                    10
                  ],
                  "uv_size": [
                    6,
                    1
                  ]
                },
                "west": {
                  "uv": [
                    10,
                    8
                  ],
                  "uv_size": [
                    4,
                    1
                  ]
                },
                "up": {
                  "uv": [
                    8,
                    6
                  ],
                  "uv_size": [
                    6,
                    4
                  ]
                },
                "down": {
                  "uv": [
                    10,
                    7
                  ],
                  "uv_size": [
                    6,
                    -4
                  ]
                }
              }
            }
          ]
        },
        {
          "name": "roof_on",
          "pivot": [
            0,
            15,
            0
          ],
          "rotation": [
            180,
            0,
            0
          ],
          "cubes": [
            {
              "origin": [
                -3,
                14,
                -2
              ],
              "size": [
                6,
                1,
                4
              ],
              "uv": {
                "north": {
                  "uv": [
                    4,
                    7
                  ],
                  "uv_size": [
                    6,
                    2
                  ]
                },
                "east": {
                  "uv": [
                    0,
                    7
                  ],
                  "uv_size": [
                    4,
                    2
                  ]
                },
                "south": {
                  "uv": [
                    10,
                    9
                  ],
                  "uv_size": [
                    6,
                    2
                  ]
                },
                "west": {
                  "uv": [
                    10,
                    7
                  ],
                  "uv_size": [
                    4,
                    2
                  ]
                },
                "up": {
                  "uv": [
                    8,
                    6
                  ],
                  "uv_size": [
                    6,
                    4
                  ]
                },
                "down": {
                  "uv": [
                    10,
                    7
                  ],
                  "uv_size": [
                    6,
                    -4
                  ]
                }
              }
            }
          ]
        }
      ]
    }
  ]
}

