{
  "format_version": "1.26.10",
  "minecraft:recipe_smithing_transform": {
    "description": {
      "identifier": "zombie:smithing_netherite_jellyfish_yellow_boots"
    },
    "unlock": [
      {
        "item": "minecraft:iron_ingot"
      },
      {
        "item": "zombie:jellyfish_jelly_yellow"
      }
    ],
    "tags": [
      "smithing_table"
    ],
    "template": "minecraft:netherite_upgrade_smithing_template",
    "base": "zombie:jellyfish_yellow_boots",
    "addition": "minecraft:netherite_ingot",
    "result": "zombie:jellyfish_netherite_yellow_boots"
  }
}

