{
	"format_version": "1.21.0",
	"minecraft:geometry": [
		{
			"description": {
				"identifier": "geometry.chaos_book_open",
				"texture_width": 32,
				"texture_height": 32,
				"visible_bounds_width": 5,
				"visible_bounds_height": 4,
				"visible_bounds_offset": [0, 1, 0]
			},
			"bones": [
				{
					"name": "root",
					"pivot": [0, 0, 0]
				},
				{
					"name": "waist",
					"parent": "root",
					"pivot": [0, 12, 0],
					"cubes": [
						{"origin": [-4, 12, -2], "size": [8, 12, 4], "uv": [59, 76]}
					]
				},
				{
					"name": "body",
					"parent": "waist",
					"pivot": [0, 24, 0]
				},
				{
					"name": "head",
					"parent": "body",
					"pivot": [0, 24, 0],
					"cubes": [
						{"origin": [-4, 24, -4], "size": [8, 8, 8], "uv": [55, 81]}
					]
				},
				{
					"name": "leftArm",
					"parent": "body",
					"pivot": [5, 22, 0],
					"cubes": [
						{"origin": [4, 12, -2], "size": [4, 12, 4], "uv": [57, 86], "mirror": true}
					]
				},
				{
					"name": "rightArm",
					"parent": "body",
					"pivot": [-5, 22, 0],
					"cubes": [
						{"origin": [-8, 12, -2], "size": [4, 12, 4], "uv": [62, 78]}
					]
				},
				{
					"name": "rightItem",
					"parent": "rightArm",
					"pivot": [-6, 14, 0]
				},
				{
					"name": "chaos_book",
					"parent": "rightItem",
					"pivot": [0.6774, 16.98207, -8.25047],
					"rotation": [90.6005, -39.82367, -89.75684],
					"cubes": [
						{
							"origin": [-1.42308, 12.165, -8.72475],
							"size": [0.925, 9.435, 0.74],
							"pivot": [1.29835, 17.1675, -8.29836],
							"rotation": [0, 22.5, 0],
							"uv": {
								"north": {"uv": [11, 20], "uv_size": [1, 9.5]},
								"east": {"uv": [21, 0], "uv_size": [0.75, 9.5]},
								"south": {"uv": [12, 20], "uv_size": [1, 9.5]},
								"west": {"uv": [21, 20], "uv_size": [0.75, 9.5]},
								"up": {"uv": [14, 28], "uv_size": [1, 0.75]},
								"down": {"uv": [28, 14.75], "uv_size": [1, -0.75]}
							}
						},
						{
							"origin": [-1.42308, 12.165, -8.61195],
							"size": [0.925, 9.435, 0.74],
							"pivot": [1.29835, 17.1675, -8.29836],
							"rotation": [0, -22.5, 0],
							"uv": {
								"north": {"uv": [19, 20], "uv_size": [1, 9.5]},
								"east": {"uv": [0, 22], "uv_size": [0.75, 9.5]},
								"south": {"uv": [20, 20], "uv_size": [1, 9.5]},
								"west": {"uv": [22, 0], "uv_size": [0.75, 9.5]},
								"up": {"uv": [15, 28], "uv_size": [1, 0.75]},
								"down": {"uv": [28, 15.75], "uv_size": [1, -0.75]}
							}
						},
						{
							"origin": [-1.3791, 12.18, -8.94586],
							"size": [0.925, 9.42, 1.29501],
							"uv": {
								"north": {"uv": [13, 20], "uv_size": [1, 9.5]},
								"east": {"uv": [7, 20], "uv_size": [1.25, 9.5]},
								"south": {"uv": [18, 20], "uv_size": [1, 9.5]},
								"west": {"uv": [9, 20], "uv_size": [1.25, 9.5]},
								"up": {"uv": [26, 20], "uv_size": [1, 1.25]},
								"down": {"uv": [22, 27.25], "uv_size": [1, -1.25]}
							}
						},
						{
							"origin": [-0.58367, 12.265, -15.01324],
							"size": [0.525, 9.435, 6.66],
							"pivot": [2.09835, 17, -9.3975],
							"rotation": [0, -22.5, 0],
							"uv": {
								"north": {"uv": [2, 22], "uv_size": [0.5, 9.5]},
								"east": {"uv": [0, 0], "uv_size": [6.75, 9.5]},
								"south": {"uv": [1, 22], "uv_size": [0.5, 9.5]},
								"west": {"uv": [7, 10], "uv_size": [6.75, 9.5]},
								"up": {"uv": [21, 10], "uv_size": [6.75, 0.5], "uv_rotation": 90},
								"down": {"uv": [21, 11.5], "uv_size": [6.75, -0.5], "uv_rotation": 270}
							}
						},
						{
							"origin": [-0.76867, 19.65, -15.44824],
							"size": [0.89501, 2.22, 0.925],
							"pivot": [2.09835, 17, -9.3975],
							"rotation": [0, -22.5, 0],
							"uv": {
								"north": {"uv": [22, 14], "uv_size": [1, 2.25]},
								"east": {"uv": [21, 14], "uv_size": [1, 2.25]},
								"south": {"uv": [5, 22], "uv_size": [1, 2.25]},
								"west": {"uv": [6, 22], "uv_size": [1, 2.25]},
								"up": {"uv": [25, 9], "uv_size": [1, 1], "uv_rotation": 90},
								"down": {"uv": [26, 10], "uv_size": [1, -1], "uv_rotation": 270}
							}
						},
						{
							"origin": [-0.76867, 20.945, -14.52324],
							"size": [0.89501, 0.925, 0.925],
							"pivot": [2.09835, 17, -9.3975],
							"rotation": [0, -22.5, 0],
							"uv": {
								"north": {"uv": [23, 17], "uv_size": [1, 1]},
								"east": {"uv": [21, 17], "uv_size": [1, 1]},
								"south": {"uv": [22, 17], "uv_size": [1, 1]},
								"west": {"uv": [23, 9], "uv_size": [1, 1]},
								"up": {"uv": [24, 9], "uv_size": [1, 1], "uv_rotation": 90},
								"down": {"uv": [24, 18], "uv_size": [1, -1], "uv_rotation": 270}
							}
						},
						{
							"origin": [-0.82963, 19.65, -8.57177],
							"size": [0.89501, 2.22, 0.925],
							"pivot": [2.09835, 17, -9.3975],
							"rotation": [0, -22.5, 0],
							"uv": {
								"north": {"uv": [25, 3], "uv_size": [1, 2.25]},
								"east": {"uv": [24, 20], "uv_size": [1, 2.25]},
								"south": {"uv": [24, 23], "uv_size": [1, 2.25]},
								"west": {"uv": [25, 0], "uv_size": [1, 2.25]},
								"up": {"uv": [28, 0], "uv_size": [1, 1], "uv_rotation": 90},
								"down": {"uv": [28, 2], "uv_size": [1, -1], "uv_rotation": 270}
							}
						},
						{
							"origin": [-0.82963, 20.945, -9.49677],
							"size": [0.89501, 0.925, 0.925],
							"pivot": [2.09835, 17, -9.3975],
							"rotation": [0, -22.5, 0],
							"uv": {
								"north": {"uv": [27, 19], "uv_size": [1, 1]},
								"east": {"uv": [17, 27], "uv_size": [1, 1]},
								"south": {"uv": [27, 17], "uv_size": [1, 1]},
								"west": {"uv": [27, 18], "uv_size": [1, 1]},
								"up": {"uv": [28, 5], "uv_size": [1, 1], "uv_rotation": 90},
								"down": {"uv": [27, 22], "uv_size": [1, -1], "uv_rotation": 270}
							}
						},
						{
							"origin": [-0.82963, 12.13, -8.57177],
							"size": [0.89501, 2.22, 0.925],
							"pivot": [2.09835, 17, -9.3975],
							"rotation": [0, -22.5, 0],
							"uv": {
								"north": {"uv": [25, 14], "uv_size": [1, 2.25]},
								"east": {"uv": [5, 25], "uv_size": [1, 2.25]},
								"south": {"uv": [6, 25], "uv_size": [1, 2.25]},
								"west": {"uv": [25, 6], "uv_size": [1, 2.25]},
								"up": {"uv": [28, 2], "uv_size": [1, -1], "uv_rotation": 90},
								"down": {"uv": [29, 14], "uv_size": [-1, -1], "uv_rotation": 270}
							}
						},
						{
							"origin": [-0.82963, 12.13, -9.49677],
							"size": [0.89501, 0.925, 0.925],
							"pivot": [2.09835, 17, -9.3975],
							"rotation": [0, -22.5, 0],
							"uv": {
								"north": {"uv": [25, 27], "uv_size": [1, 1]},
								"east": {"uv": [27, 23], "uv_size": [1, 1]},
								"south": {"uv": [24, 27], "uv_size": [1, 1]},
								"west": {"uv": [27, 24], "uv_size": [1, 1]},
								"up": {"uv": [27, 25], "uv_size": [1, 1], "uv_rotation": 90},
								"down": {"uv": [29, 12], "uv_size": [-1, -1], "uv_rotation": 270}
							}
						},
						{
							"origin": [-0.89751, 12.13, -8.58207],
							"size": [0.89501, 2.22, 0.925],
							"pivot": [2.09835, 17, -7.18133],
							"rotation": [0, 22.5, 0],
							"uv": {
								"north": {"uv": [26, 6], "uv_size": [1, 2.25]},
								"east": {"uv": [26, 14], "uv_size": [1, 2.25]},
								"south": {"uv": [26, 17], "uv_size": [1, 2.25]},
								"west": {"uv": [26, 3], "uv_size": [1, 2.25]},
								"up": {"uv": [28, 12], "uv_size": [1, 1], "uv_rotation": 270},
								"down": {"uv": [29, 14], "uv_size": [-1, -1], "uv_rotation": 90}
							}
						},
						{
							"origin": [-0.89751, 12.13, -7.65707],
							"size": [0.89501, 0.925, 0.925],
							"pivot": [2.09835, 17, -7.18133],
							"rotation": [0, 22.5, 0],
							"uv": {
								"north": {"uv": [28, 7], "uv_size": [1, 1]},
								"east": {"uv": [28, 8], "uv_size": [1, 1]},
								"south": {"uv": [28, 9], "uv_size": [1, 1]},
								"west": {"uv": [28, 6], "uv_size": [1, 1]},
								"up": {"uv": [28, 10], "uv_size": [1, 1], "uv_rotation": 270},
								"down": {"uv": [29, 12], "uv_size": [-1, -1], "uv_rotation": 90}
							}
						},
						{
							"origin": [-0.89751, 20.945, -7.90707],
							"size": [0.89501, 0.925, 0.925],
							"pivot": [2.09835, 17, -7.18133],
							"rotation": [0, 22.5, 0],
							"uv": {
								"north": {"uv": [28, 3], "uv_size": [1, 1]},
								"east": {"uv": [28, 4], "uv_size": [1, 1]},
								"south": {"uv": [5, 28], "uv_size": [1, 1]},
								"west": {"uv": [28, 2], "uv_size": [1, 1]},
								"up": {"uv": [28, 5], "uv_size": [1, 1], "uv_rotation": 270},
								"down": {"uv": [6, 29], "uv_size": [1, -1], "uv_rotation": 90}
							}
						},
						{
							"origin": [-0.89751, 19.65, -8.83207],
							"size": [0.89501, 2.22, 0.925],
							"pivot": [2.09835, 17, -7.18133],
							"rotation": [0, 22.5, 0],
							"uv": {
								"north": {"uv": [25, 20], "uv_size": [1, 2.25]},
								"east": {"uv": [25, 23], "uv_size": [1, 2.25]},
								"south": {"uv": [26, 0], "uv_size": [1, 2.25]},
								"west": {"uv": [25, 17], "uv_size": [1, 2.25]},
								"up": {"uv": [28, 0], "uv_size": [1, 1], "uv_rotation": 270},
								"down": {"uv": [28, 2], "uv_size": [1, -1], "uv_rotation": 90}
							}
						},
						{
							"origin": [-0.76867, 12.13, -15.44824],
							"size": [0.89501, 2.22, 0.925],
							"pivot": [2.09835, 17, -9.3975],
							"rotation": [0, -22.5, 0],
							"uv": {
								"north": {"uv": [23, 6], "uv_size": [1, 2.25]},
								"east": {"uv": [22, 20], "uv_size": [1, 2.25]},
								"south": {"uv": [23, 0], "uv_size": [1, 2.25]},
								"west": {"uv": [23, 3], "uv_size": [1, 2.25]},
								"up": {"uv": [26, 25], "uv_size": [1, 1], "uv_rotation": 90},
								"down": {"uv": [29, 12], "uv_size": [-1, -1], "uv_rotation": 270}
							}
						},
						{
							"origin": [-0.76867, 12.13, -14.52324],
							"size": [0.89501, 0.925, 0.925],
							"pivot": [2.09835, 17, -9.3975],
							"rotation": [0, -22.5, 0],
							"uv": {
								"north": {"uv": [24, 26], "uv_size": [1, 1]},
								"east": {"uv": [26, 22], "uv_size": [1, 1]},
								"south": {"uv": [23, 26], "uv_size": [1, 1]},
								"west": {"uv": [26, 23], "uv_size": [1, 1]},
								"up": {"uv": [26, 24], "uv_size": [1, 1], "uv_rotation": 90},
								"down": {"uv": [29, 14], "uv_size": [-1, -1], "uv_rotation": 270}
							}
						},
						{
							"origin": [-0.61579, 12.265, -8.12559],
							"size": [0.525, 9.435, 6.66],
							"pivot": [2.09835, 17, -7.18133],
							"rotation": [0, 22.5, 0],
							"uv": {
								"north": {"uv": [3, 22], "uv_size": [0.5, 9.5]},
								"east": {"uv": [7, 10], "uv_size": [6.75, 9.5]},
								"south": {"uv": [4, 22], "uv_size": [0.5, 9.5]},
								"west": {"uv": [13.75, 10], "uv_size": [-6.75, 9.5]},
								"up": {"uv": [21, 10.5], "uv_size": [6.75, -0.5], "uv_rotation": 270},
								"down": {"uv": [21, 13.5], "uv_size": [6.75, -0.5], "uv_rotation": 90}
							}
						},
						{
							"origin": [-0.80079, 20.945, -2.88059],
							"size": [0.895, 0.925, 0.925],
							"pivot": [2.09835, 17, -7.18133],
							"rotation": [0, 22.5, 0],
							"uv": {
								"north": {"uv": [27, 14], "uv_size": [1, 1]},
								"east": {"uv": [15, 27], "uv_size": [1, 1]},
								"south": {"uv": [27, 15], "uv_size": [1, 1]},
								"west": {"uv": [14, 27], "uv_size": [1, 1]},
								"up": {"uv": [16, 27], "uv_size": [1, 1], "uv_rotation": 270},
								"down": {"uv": [27, 17], "uv_size": [1, -1], "uv_rotation": 90}
							}
						},
						{
							"origin": [-0.80079, 19.65, -1.95559],
							"size": [0.895, 2.22, 0.925],
							"pivot": [2.09835, 17, -7.18133],
							"rotation": [0, 22.5, 0],
							"uv": {
								"north": {"uv": [24, 3], "uv_size": [1, 2.25]},
								"east": {"uv": [24, 6], "uv_size": [1, 2.25]},
								"south": {"uv": [24, 14], "uv_size": [1, 2.25]},
								"west": {"uv": [24, 0], "uv_size": [1, 2.25]},
								"up": {"uv": [27, 8], "uv_size": [1, 1], "uv_rotation": 270},
								"down": {"uv": [28, 2], "uv_size": [1, -1], "uv_rotation": 90}
							}
						},
						{
							"origin": [-0.80079, 12.13, -2.88059],
							"size": [0.895, 0.925, 0.925],
							"pivot": [2.09835, 17, -7.18133],
							"rotation": [0, 22.5, 0],
							"uv": {
								"north": {"uv": [27, 3], "uv_size": [1, 1]},
								"east": {"uv": [27, 4], "uv_size": [1, 1]},
								"south": {"uv": [27, 5], "uv_size": [1, 1]},
								"west": {"uv": [27, 2], "uv_size": [1, 1]},
								"up": {"uv": [27, 6], "uv_size": [1, 1], "uv_rotation": 270},
								"down": {"uv": [28, 8], "uv_size": [-1, -1], "uv_rotation": 90}
							}
						},
						{
							"origin": [-0.80079, 12.13, -1.95559],
							"size": [0.895, 2.22, 0.925],
							"pivot": [2.09835, 17, -7.18133],
							"rotation": [0, 22.5, 0],
							"uv": {
								"north": {"uv": [23, 20], "uv_size": [1, 2.25]},
								"east": {"uv": [22, 23], "uv_size": [1, 2.25]},
								"south": {"uv": [23, 23], "uv_size": [1, 2.25]},
								"west": {"uv": [23, 14], "uv_size": [1, 2.25]},
								"up": {"uv": [27, 0], "uv_size": [1, 1], "uv_rotation": 270},
								"down": {"uv": [29, 12], "uv_size": [-1, -1], "uv_rotation": 90}
							}
						},
						{
							"origin": [-0.06713, 12.45, -13.37103],
							"size": [0, 9.065, 6.16],
							"pivot": [2.58287, 16.9825, -8.64103],
							"rotation": [0, -22.5, 0],
							"uv": {
								"north": {"uv": [16, 18], "uv_size": [2, 9]},
								"east": {"uv": [14, 0], "uv_size": [6.25, 9]},
								"south": {"uv": [14, 18], "uv_size": [2, 9]},
								"west": {"uv": [20.25, 0], "uv_size": [-6.25, 9]},
								"up": {"uv": [0, 22], "uv_size": [6.25, -2], "uv_rotation": 90},
								"down": {"uv": [6.25, 20], "uv_size": [-6.25, 2], "uv_rotation": 270}
							}
						},
						{
							"origin": [-0.56713, 12.45, -9.53897],
							"size": [0, 9.065, 6.16],
							"pivot": [2.58287, 16.9825, -9.35897],
							"rotation": [0, 22.5, 0],
							"uv": {
								"north": {"uv": [16, 18], "uv_size": [-2, 9]},
								"east": {"uv": [20.25, 0], "uv_size": [-6.25, 9]},
								"south": {"uv": [18, 18], "uv_size": [-2, 9]},
								"west": {"uv": [14, 0], "uv_size": [6.25, 9]},
								"up": {"uv": [6.25, 22], "uv_size": [-6.25, -2], "uv_rotation": 90},
								"down": {"uv": [0, 20], "uv_size": [6.25, 2], "uv_rotation": 270}
							}
						},
						{
							"origin": [0.13287, 12.45, -13.37103],
							"size": [0, 9.065, 6.16],
							"pivot": [2.78287, 16.9825, -8.64103],
							"rotation": [0, -22.5, 0],
							"uv": {
								"north": {"uv": [16, 18], "uv_size": [2, 9]},
								"east": {"uv": [14, 0], "uv_size": [6.25, 9]},
								"south": {"uv": [14, 18], "uv_size": [2, 9]},
								"west": {"uv": [20.25, 0], "uv_size": [-6.25, 9]},
								"up": {"uv": [0, 22], "uv_size": [6.25, -2], "uv_rotation": 90},
								"down": {"uv": [6.25, 20], "uv_size": [-6.25, 2], "uv_rotation": 270}
							}
						},
						{
							"origin": [-0.36713, 12.45, -9.53897],
							"size": [0, 9.065, 6.16],
							"pivot": [2.78287, 16.9825, -9.35897],
							"rotation": [0, 22.5, 0],
							"uv": {
								"north": {"uv": [16, 18], "uv_size": [-2, 9]},
								"east": {"uv": [20.25, 0], "uv_size": [-6.25, 9]},
								"south": {"uv": [18, 18], "uv_size": [-2, 9]},
								"west": {"uv": [14, 0], "uv_size": [6.25, 9]},
								"up": {"uv": [6.25, 22], "uv_size": [-6.25, -2], "uv_rotation": 90},
								"down": {"uv": [0, 20], "uv_size": [6.25, 2], "uv_rotation": 270}
							}
						},
						{
							"origin": [0.33287, 12.45, -13.37103],
							"size": [0, 9.065, 6.16],
							"pivot": [2.98287, 16.9825, -8.64103],
							"rotation": [0, -22.5, 0],
							"uv": {
								"north": {"uv": [16, 18], "uv_size": [2, 9]},
								"east": {"uv": [14, 0], "uv_size": [6.25, 9]},
								"south": {"uv": [14, 18], "uv_size": [2, 9]},
								"west": {"uv": [20.25, 0], "uv_size": [-6.25, 9]},
								"up": {"uv": [0, 22], "uv_size": [6.25, -2], "uv_rotation": 90},
								"down": {"uv": [6.25, 20], "uv_size": [-6.25, 2], "uv_rotation": 270}
							}
						},
						{
							"origin": [2.28557, 12.45, -14.10647],
							"size": [0, 9.065, 6.16],
							"pivot": [1.53557, 16.9825, -11.02647],
							"rotation": [0, -45, 0],
							"uv": {
								"north": {"uv": [16, 18], "uv_size": [2, 9]},
								"east": {"uv": [14, 0], "uv_size": [6.25, 9]},
								"south": {"uv": [14, 18], "uv_size": [2, 9]},
								"west": {"uv": [20.25, 0], "uv_size": [-6.25, 9]},
								"up": {"uv": [0, 22], "uv_size": [6.25, -2], "uv_rotation": 90},
								"down": {"uv": [6.25, 20], "uv_size": [-6.25, 2], "uv_rotation": 270}
							}
						},
						{
							"origin": [1.38557, 12.45, -9.05353],
							"size": [0, 9.065, 6.16],
							"pivot": [1.53557, 16.9825, -6.97353],
							"rotation": [0, 45, 0],
							"uv": {
								"north": {"uv": [16, 18], "uv_size": [-2, 9]},
								"east": {"uv": [20.25, 0], "uv_size": [-6.25, 9]},
								"south": {"uv": [18, 18], "uv_size": [-2, 9]},
								"west": {"uv": [14, 0], "uv_size": [6.25, 9]},
								"up": {"uv": [6.25, 22], "uv_size": [-6.25, -2], "uv_rotation": 90},
								"down": {"uv": [0, 20], "uv_size": [6.25, 2], "uv_rotation": 270}
							}
						},
						{
							"origin": [-0.16713, 12.45, -9.53897],
							"size": [0, 9.065, 6.16],
							"pivot": [2.98287, 16.9825, -9.35897],
							"rotation": [0, 22.5, 0],
							"uv": {
								"north": {"uv": [16, 18], "uv_size": [-2, 9]},
								"east": {"uv": [20.25, 0], "uv_size": [-6.25, 9]},
								"south": {"uv": [18, 18], "uv_size": [-2, 9]},
								"west": {"uv": [14, 0], "uv_size": [6.25, 9]},
								"up": {"uv": [6.25, 22], "uv_size": [-6.25, -2], "uv_rotation": 90},
								"down": {"uv": [0, 20], "uv_size": [6.25, 2], "uv_rotation": 270}
							}
						}
					]
				},
				{
					"name": "rightLeg",
					"parent": "root",
					"pivot": [-1.9, 12, 0],
					"cubes": [
						{"origin": [-4, 0, -2], "size": [4, 12, 4], "uv": [57, 87], "mirror": true}
					]
				},
				{
					"name": "leftLeg",
					"parent": "root",
					"pivot": [1.9, 12, 0],
					"cubes": [
						{"origin": [0, 0, -2], "size": [4, 12, 4], "uv": [56, 84]}
					]
				}
			],
			"item_display_transforms": {
				"thirdperson_righthand": {
					"rotation": [0, 90, 0],
					"translation": [-0.75, 4.25, 1.75],
					"scale": [1, 1, 1],
					"rotation_pivot": [0, 0, 0],
					"scale_pivot": [0, 0, 0]
				},
				"thirdperson_lefthand": {
					"rotation": [0, -90, 0],
					"translation": [0, 4.25, 1.75],
					"scale": [1, 1, 1],
					"rotation_pivot": [0, 0, 0],
					"scale_pivot": [0, 0, 0]
				},
				"firstperson_righthand": {
					"rotation": [0, 85, 0],
					"translation": [-0.5, 4.25, 0],
					"scale": [1, 1, 1],
					"rotation_pivot": [0, 0, 0],
					"scale_pivot": [0, 0, 0]
				},
				"firstperson_lefthand": {
					"rotation": [0, -115, 0],
					"translation": [1.25, 4.25, 0],
					"scale": [1, 1, 1],
					"rotation_pivot": [0, 0, 0],
					"scale_pivot": [0, 0, 0]
				},
				"ground": {
					"rotation": [0, 0, -55],
					"translation": [0, 1.25, 0],
					"scale": [1, 1, 1],
					"rotation_pivot": [0, 0, 0],
					"scale_pivot": [0, 0, 0]
				},
				"gui": {
					"rotation": [0, 90, 0],
					"translation": [-0.75, 0, 0],
					"scale": [1.02, 1.02, 1.02],
					"rotation_pivot": [0, 0, 0],
					"scale_pivot": [0, 0, 0],
					"fit_to_frame": false
				},
				"fixed": {
					"rotation": [0, -90, 0],
					"translation": [1.5, 0, -6.25],
					"scale": [2.23, 2.23, 2.23],
					"rotation_pivot": [0, 0, 0],
					"scale_pivot": [0, 0, 0]
				}
			}
		}
	]
}